radiocarbon/__init__.py
radiocarbon/calibration_curves.py
radiocarbon/date.py
radiocarbon/spd.py
radiocarbon/calcurves/intcal13.14c
radiocarbon/calcurves/intcal20.14c
radiocarbon/calcurves/marine13.14c
radiocarbon/calcurves/marine20.14c
radiocarbon/calcurves/shcal13.14c
radiocarbon/calcurves/shcal20.14c
radiocarbon-0.5.0.dist-info/METADATA
radiocarbon-0.5.0.dist-info/WHEEL
radiocarbon-0.5.0.dist-info/top_level.txt
radiocarbon-0.5.0.dist-info/RECORD
