Metadata-Version: 2.1
Name: radiocarbon
Version: 0.5.0
Summary: A package for calibrating radiocarbon dates, calculating summed probability distributions, and testing their significance against a null hypothesis.
Home-page: https://github.com/jgregoriods/radiocarbon
Author: Jonas Gregorio
License: GNU General Public License v3.0 only
Classifier: Programming Language :: Python :: 3
Classifier: License :: OSI Approved :: GNU General Public License v3 (GPLv3)
Classifier: Operating System :: OS Independent
Requires-Python: >=3.8
